markdown_renderer_lite/__init__.py
markdown_renderer_lite/__main__.py
markdown_renderer_lite/converter.py
markdown_renderer_lite-0.2.0.dist-info/METADATA
markdown_renderer_lite-0.2.0.dist-info/WHEEL
markdown_renderer_lite-0.2.0.dist-info/entry_points.txt
markdown_renderer_lite-0.2.0.dist-info/top_level.txt
markdown_renderer_lite-0.2.0.dist-info/RECORD
