Metadata-Version: 2.2
Name: markdown-renderer-lite
Version: 0.2.0
Summary: A lightweight Markdown to HTML converter with syntax highlighting.
Home-page: https://github.com/orhancavus/markdown_renderer_lite
Author: Orhan Cavus
Author-email: orhancv@gmail.com
Classifier: Programming Language :: Python :: 3
Classifier: License :: OSI Approved :: MIT License
Classifier: Operating System :: OS Independent
Requires-Python: >=3.6
Requires-Dist: markdown
Dynamic: author
Dynamic: author-email
Dynamic: classifier
Dynamic: description
Dynamic: description-content-type
Dynamic: home-page
Dynamic: requires-dist
Dynamic: requires-python
Dynamic: summary
